pathway_viz-0.3.1.dist-info/METADATA
pathway_viz-0.3.1.dist-info/WHEEL
pathway_viz-0.3.1.dist-info/entry_points.txt
pathway_viz-0.3.1.dist-info/licenses/LICENSE
pathwayviz/__init__.py
pathwayviz/__main__.py
pathwayviz/_pathwayviz.abi3.so
pathwayviz/_server.py
pathwayviz/_widgets.py
pathwayviz/demos/__init__.py
pathwayviz/demos/pathway.py
pathwayviz/demos/portal.html
pathwayviz/docker/__init__.py
pathwayviz/docker/docker-compose.yml
pathway_viz-0.3.1.dist-info/RECORD
