Metadata-Version: 2.4
Name: pathway-viz
Version: 0.3.1
Classifier: Development Status :: 3 - Alpha
Classifier: Intended Audience :: Developers
Classifier: License :: OSI Approved :: MIT License
Classifier: Programming Language :: Python :: 3
Classifier: Programming Language :: Python :: 3.11
Classifier: Programming Language :: Python :: 3.12
Classifier: Programming Language :: Python :: 3.13
Classifier: Programming Language :: Rust
Classifier: Topic :: Scientific/Engineering :: Visualization
Classifier: Topic :: System :: Monitoring
Requires-Dist: pathway>=0.8 ; python_full_version < '3.14'
Requires-Dist: kafka-python-ng>=2.0 ; extra == 'kafka'
Requires-Dist: kafka-python-ng>=2.0 ; extra == 'all'
Requires-Dist: pytest>=7.0 ; extra == 'dev'
Requires-Dist: ruff>=0.1 ; extra == 'dev'
Requires-Dist: maturin>=1.0,<2.0 ; extra == 'dev'
Provides-Extra: kafka
Provides-Extra: all
Provides-Extra: dev
License-File: LICENSE
Summary: The visualization layer for Pathway - real-time dashboards for streaming data
Keywords: streaming,visualization,pathway,kafka,real-time,dashboard
License: MIT
Requires-Python: >=3.11
Project-URL: Homepage, https://github.com/mvfolino68/pathway-viz
Project-URL: Repository, https://github.com/mvfolino68/pathway-viz
Project-URL: Documentation, https://github.com/mvfolino68/pathway-viz#readme
Project-URL: Issues, https://github.com/mvfolino68/pathway-viz/issues
